fastapi_redis_session/__init__.py
fastapi_redis_session/config.py
fastapi_redis_session/deps.py
fastapi_redis_session/session.py
fastapi_redis_session-0.1.5.dist-info/WHEEL
fastapi_redis_session-0.1.5.dist-info/METADATA
fastapi_redis_session-0.1.5.dist-info/RECORD
