Metadata-Version: 2.1
Name: fastapi-redis-session
Version: 0.1.5
Summary: A redis-based session backend for Fastapi apps
Home-page: https://github.com/duyixian1234/fastapi-redis-session
License: MIT
Author: duyixian
Author-email: duyixian1234@qq.com
Requires-Python: >=3.7,<4.0
Classifier: License :: OSI Approved :: MIT License
Classifier: Programming Language :: Python :: 3
Classifier: Programming Language :: Python :: 3.7
Classifier: Programming Language :: Python :: 3.8
Classifier: Programming Language :: Python :: 3.9
Requires-Dist: fastapi (>=0.63.0,<0.64.0)
Requires-Dist: redis (>=3.5.3,<4.0.0)
Project-URL: Repository, https://github.com/duyixian1234/fastapi-redis-session
